__sdl.pyd
__sdl_image.pyd
__sdl_mixer.pyd
__sdl_ttf.pyd
pysdl2_cffi-0.8.0.dist-info/DESCRIPTION.rst
pysdl2_cffi-0.8.0.dist-info/LICENSE.txt
pysdl2_cffi-0.8.0.dist-info/METADATA
pysdl2_cffi-0.8.0.dist-info/metadata.json
pysdl2_cffi-0.8.0.dist-info/RECORD
pysdl2_cffi-0.8.0.dist-info/top_level.txt
pysdl2_cffi-0.8.0.dist-info/WHEEL
sdl/__init__.py
_sdl/autohelpers.py
_sdl/cdefs.py
_sdl/constants.py
_sdl/defines.h
_sdl/helpers.py
_sdl/lib.py
_sdl/pixels.py
_sdl/renamed.py
_sdl/renamer.py
_sdl/sdl.h
_sdl/structs.py
_sdl/__init__.py
_sdl_image/autohelpers.py
_sdl_image/cdefs.py
_sdl_image/lib.py
_sdl_image/renamed.py
_sdl_image/structs.py
_sdl_image/__init__.py
_sdl_mixer/autohelpers.py
_sdl_mixer/cdefs.py
_sdl_mixer/constants.py
_sdl_mixer/lib.py
_sdl_mixer/renamed.py
_sdl_mixer/structs.py
_sdl_mixer/__init__.py
_sdl_ttf/autohelpers.py
_sdl_ttf/cdefs.py
_sdl_ttf/lib.py
_sdl_ttf/renamed.py
_sdl_ttf/structs.py
_sdl_ttf/__init__.py
