Metadata-Version: 2.0
Name: pysdl2-cffi
Version: 0.8.0
Summary: SDL2 wrapper with cffi
Home-page: https://bitbucket.org/dholth/pysdl2-cffi
Author: Daniel Holth
Author-email: dholth@fastmail.fm
License: GPLv2+
Keywords: sdl,cffi>=1.1
Platform: UNKNOWN
Classifier: Programming Language :: Python :: 2.7
Classifier: Programming Language :: Python :: 3
Classifier: Programming Language :: Python :: 3.4
Classifier: License :: OSI Approved :: GNU General Public License v2 or later (GPLv2+)
Requires-Dist: cffi (>=1.1.0)
Requires-Dist: apipkg
Requires-Dist: sdl2-lib; sys_platform=="win32"
Provides-Extra: build
Requires-Dist: pycparser; extra == 'build'
